sciop-202503.18.1.dist-info/METADATA
sciop-202503.18.1.dist-info/WHEEL
sciop-202503.18.1.dist-info/entry_points.txt
sciop-202503.18.1.dist-info/licenses/LICENSE
sciop/.DS_Store
sciop/__init__.py
sciop/__main__.py
sciop/_version.py
sciop/api/__init__.py
sciop/api/auth.py
sciop/api/deps.py
sciop/api/main.py
sciop/api/routes/__init__.py
sciop/api/routes/datasets.py
sciop/api/routes/login.py
sciop/api/routes/review.py
sciop/api/routes/tags.py
sciop/api/routes/upload.py
sciop/api/routes/uploads.py
sciop/app.py
sciop/config.py
sciop/const.py
sciop/crud.py
sciop/db.py
sciop/docs/404.html
sciop/docs/assets/images/favicon.png
sciop/docs/assets/javascripts/bundle.f1b6f286.min.js
sciop/docs/assets/javascripts/bundle.f1b6f286.min.js.map
sciop/docs/assets/javascripts/lunr/min/lunr.ar.min.js
sciop/docs/assets/javascripts/lunr/min/lunr.da.min.js
sciop/docs/assets/javascripts/lunr/min/lunr.de.min.js
sciop/docs/assets/javascripts/lunr/min/lunr.du.min.js
sciop/docs/assets/javascripts/lunr/min/lunr.el.min.js
sciop/docs/assets/javascripts/lunr/min/lunr.es.min.js
sciop/docs/assets/javascripts/lunr/min/lunr.fi.min.js
sciop/docs/assets/javascripts/lunr/min/lunr.fr.min.js
sciop/docs/assets/javascripts/lunr/min/lunr.he.min.js
sciop/docs/assets/javascripts/lunr/min/lunr.hi.min.js
sciop/docs/assets/javascripts/lunr/min/lunr.hu.min.js
sciop/docs/assets/javascripts/lunr/min/lunr.hy.min.js
sciop/docs/assets/javascripts/lunr/min/lunr.it.min.js
sciop/docs/assets/javascripts/lunr/min/lunr.ja.min.js
sciop/docs/assets/javascripts/lunr/min/lunr.jp.min.js
sciop/docs/assets/javascripts/lunr/min/lunr.kn.min.js
sciop/docs/assets/javascripts/lunr/min/lunr.ko.min.js
sciop/docs/assets/javascripts/lunr/min/lunr.multi.min.js
sciop/docs/assets/javascripts/lunr/min/lunr.nl.min.js
sciop/docs/assets/javascripts/lunr/min/lunr.no.min.js
sciop/docs/assets/javascripts/lunr/min/lunr.pt.min.js
sciop/docs/assets/javascripts/lunr/min/lunr.ro.min.js
sciop/docs/assets/javascripts/lunr/min/lunr.ru.min.js
sciop/docs/assets/javascripts/lunr/min/lunr.sa.min.js
sciop/docs/assets/javascripts/lunr/min/lunr.stemmer.support.min.js
sciop/docs/assets/javascripts/lunr/min/lunr.sv.min.js
sciop-202503.18.1.dist-info/RECORD
