Metadata-Version: 2.1
Name: sciop
Version: 202503.18.1
Summary: Default template for PDM package
Author-Email: sneakers-the-rat <sneakers-the-rat@protonmail.com>
License: EUPL-1.2
Requires-Python: >=3.11
Requires-Dist: fastapi>=0.115.8
Requires-Dist: sqlmodel>=0.0.22
Requires-Dist: pydantic-settings>=2.7.1
Requires-Dist: uvicorn>=0.34.0
Requires-Dist: jinja2>=3.1.5
Requires-Dist: alembic>=1.14.1
Requires-Dist: lxml>=5.3.0
Requires-Dist: pydantic>=2.10.6
Requires-Dist: rich>=13.9.4
Requires-Dist: platformdirs>=4.3.6
Requires-Dist: pyjwt>=2.10.1
Requires-Dist: python-multipart>=0.0.20
Requires-Dist: bcrypt>=4.2.1
Requires-Dist: fastapi-pagination>=0.12.34
Requires-Dist: torf>=4.2.7
Requires-Dist: humanize>=4.11.0
Requires-Dist: slowapi>=0.1.9
Requires-Dist: fasthx>=2.1.1
Requires-Dist: faker>=35.2.0
Requires-Dist: python-slugify>=8.0.4
Requires-Dist: mkdocs-material>=9.6.4
Requires-Dist: rdflib>=7.1.3
Requires-Dist: content-negotiation>=1.1.2
Requires-Dist: bencode-py>=4.0.0
Requires-Dist: pymdown-extensions>=10.14.3
Requires-Dist: apscheduler>=3.11.0
Requires-Dist: aiodns>=3.2.0
Requires-Dist: mistune>=3.1.2
Requires-Dist: bleach>=6.2.0
Requires-Dist: pygments>=2.19.1
Provides-Extra: test
Requires-Dist: pytest>=8.3.4; extra == "test"
Requires-Dist: httpx>=0.28.1; extra == "test"
Requires-Dist: webdriver-manager>=4.0.2; extra == "test"
Requires-Dist: selenium>=4.28.1; extra == "test"
Requires-Dist: pytest-asyncio>=0.25.3; extra == "test"
Requires-Dist: beautifulsoup4>=4.13.3; extra == "test"
Requires-Dist: lxml>=5.3.1; extra == "test"
Requires-Dist: pytest-alembic>=0.11.1; extra == "test"
Requires-Dist: pytest-timeout>=2.3.1; extra == "test"
Provides-Extra: dev
Requires-Dist: sciop[test]; extra == "dev"
Requires-Dist: ruff>=0.9.4; extra == "dev"
Requires-Dist: black>=25.1.0; extra == "dev"
